MANIFEST.in
README.rst
setup.cfg
setup.py
cadcetrans/__init__.py
cadcetrans/data_verify.py
cadcetrans/etrans_core.py
cadcetrans/meta_verify.py
cadcetrans/namecheck.py
cadcetrans/utils.py
cadcetrans/version.py
cadcetrans.egg-info/PKG-INFO
cadcetrans.egg-info/SOURCES.txt
cadcetrans.egg-info/dependency_links.txt
cadcetrans.egg-info/entry_points.txt
cadcetrans.egg-info/not-zip-safe
cadcetrans.egg-info/requires.txt
cadcetrans.egg-info/top_level.txt
cadcetrans/data/default-cadcetrans-config
cadcetrans/data/namecheck.xml